{
    "description": "Now with more color and randomness.",
    "world_xz": 9,
    "world_y": 15,
    "shapes": [
        {
            "name": ">:-D",
			"lifts": 0,
            "rotatable": 0,
			"highdice": 0,
            "color": "#FF0000; Red",
            "cubed": 3,
            "blocks": [
                0, 0, 0,
                0, 0, 0,
                0, 0, 0,
                
                0, 0, 0,
                0, 1, 0,
                0, 0, 0,
                
                0, 0, 0,
                0, 0, 0,
                0, 0, 0
            ]
        },
        {
            "name": "8o)",
			"lifts": 0,
            "rotatable": 1,
			"highdice": 0,
            "color": "#00FF00; Green",
            "cubed": 3,
            "blocks": [
                0, 0, 0,
                0, 1, 0,
                0, 0, 0,
                
                0, 0, 0,
                0, 1, 0,
                0, 0, 0,
                
                0, 0, 0,
                0, 1, 1,
                0, 0, 0
            ]
        },
        {
            "name": ":-D",
			"lifts": 0,
            "rotatable": 1,
			"highdice": 0,
            "color": "#0000FF; Blue",
            "cubed": 3,
            "blocks": [
                0, 0, 0,
                0, 1, 1,
                0, 0, 0,
                
                0, 0, 0,
                1, 1, 0,
                0, 0, 0,
                
                0, 0, 0,
                0, 0, 0,
                0, 0, 0
            ]
        },
        {
            "name": "#:-D",
			"lifts": 0,
            "rotatable": 1,
			"highdice": 0,
            "color": "#FFFF00; Yellow",
            "cubed": 3,
            "blocks": [
                0, 0, 0,
                0, 1, 0,
                0, 0, 0,
                
                0, 0, 0,
                0, 1, 0,
                0, 0, 0,
                
                0, 0, 0,
                0, 0, 0,
                0, 0, 0
            ]
        },
        {
            "name": "|:-)",
			"lifts": 0,
            "rotatable": 1,
			"highdice": 0,
            "color": "#FF00FF; Magenta",
            "cubed": 3,
            "blocks": [
                0, 0, 0,
                0, 1, 0,
                0, 0, 0,
                
                0, 0, 0,
                1, 1, 1,
                0, 0, 0,
                
                0, 0, 0,
                0, 0, 0,
                0, 0, 0
            ]
        },
        {
            "name": ":D",
			"lifts": 0,
            "rotatable": 1,
			"highdice": 0,
            "color": "#00FFFF; Cyan",
            "cubed": 3,
            "blocks": [
                0, 0, 0,
                0, 1, 0,
                0, 0, 0,
                
                0, 1, 0,
                1, 1, 0,
                0, 0, 0,
                
                0, 0, 0,
                0, 0, 0,
                0, 0, 0
            ]
        },
        {
            "name": ">:)",
			"lifts": 0,
            "rotatable": 1,
			"highdice": 0,
            "color": "#800080; Purple",
            "cubed": 3,
            "blocks": [
                0, 0, 0,
                0, 1, 0,
                0, 0, 0,
                
                0, 0, 0,
                0, 0, 0,
                0, 0, 0,
                
                0, 0, 0,
                0, 1, 0,
                0, 0, 0
            ]
        },
        {
            "name": ">:O",
			"lifts": 0,
            "rotatable": 1,
			"highdice": 0,
            "color": "#006400; DarkGreen",
            "cubed": 3,
            "blocks": [
                0, 0, 0,
                0, 1, 0,
                0, 0, 0,
                
                0, 0, 0,
                1, 0, 1,
                0, 0, 0,
                
                0, 0, 0,
                0, 0, 0,
                0, 0, 0
            ]
        },
        {
            "name": ";-/",
			"lifts": 0,
            "rotatable": 1,
			"highdice": 0,
            "color": "#800000; Maroon",
            "cubed": 3,
            "blocks": [
                0, 0, 0,
                0, 1, 0,
                0, 0, 0,
                
                0, 0, 0,
                1, 1, 0,
                0, 0, 0,
                
                0, 0, 0,
                0, 0, 0,
                0, 0, 0
            ]
        },
        {
            "name": "=-D",
			"lifts": 0,
            "rotatable": 1,
			"highdice": 0,
            "color": "#008080; Teal",
            "cubed": 3,
            "blocks": [
                0, 0, 0,
                0, 1, 0,
                0, 0, 0,
                
                0, 0, 0,
                0, 1, 0,
                0, 0, 0,
                
                0, 0, 0,
                0, 1, 0,
                0, 0, 0
            ]
        },
        {
            "name": "(-:] - [:-D",
			"lifts": 0,
            "rotatable": 1,
			"highdice": 0,
            "color": "#808000; Olive",
            "cubed": 3,
            "blocks": [
                1, 0, 0,
                0, 0, 0,
                0, 0, 0,
                
                1, 0, 0,
                0, 0, 0,
                0, 0, 1,
                
                0, 0, 0,
                0, 0, 0,
                0, 0, 1
            ]
        },
        {
            "name": ")-:] - [:-)",
			"lifts": 0,
            "rotatable": 1,
			"highdice": 0,
            "color": "#FFD700; Gold",
            "cubed": 3,
            "blocks": [
                1, 0, 0,
                0, 0, 0,
                0, 0, 0,
                
                0, 0, 0,
                0, 0, 0,
                0, 0, 0,
                
                0, 0, 0,
                0, 0, 0,
                0, 0, 1
            ]
        },
        {
            "name": ">:D",
			"lifts": 0,
            "rotatable": 1,
			"highdice": 0,
            "color": "#FF0000; Red",
            "cubed": 3,
            "blocks": [
                0, 1, 0,
                0, 1, 0,
                0, 0, 0,
                
                0, 0, 0,
                1, 1, 0,
                0, 0, 0,
                
                0, 0, 0,
                0, 0, 0,
                0, 0, 0
            ]
        },
        {
            "name": ">:-|",
			"lifts": 0,
            "rotatable": 1,
			"highdice": 0,
            "color": "#00FF00; Green",
            "cubed": 3,
            "blocks": [
                0, 0, 0,
                1, 1, 1,
                0, 0, 0,
                
                0, 0, 0,
                0, 1, 0,
                0, 0, 0,
                
                0, 0, 0,
                0, 1, 0,
                0, 0, 0
            ]
        },
        {
            "name": "|8o",
			"lifts": 0,
            "rotatable": 1,
			"highdice": 0,
            "color": "#0000FF; Blue",
            "cubed": 3,
            "blocks": [
                0, 0, 0,
                0, 0, 0,
                0, 1, 0,
                
                0, 0, 0,
                0, 1, 0,
                0, 0, 0,
                
                0, 0, 0,
                0, 0, 0,
                0, 0, 0
            ]
        },
        {
            "name": "|8)",
			"lifts": 0,
            "rotatable": 1,
			"highdice": 0,
            "color": "#FFFF00; Yellow",
            "cubed": 2,
            "blocks": [
                1, 1,
                1, 1,
                
                1, 1,
                1, 1
            ]
        },
        {
            "name": "|8>",
			"lifts": 0,
            "rotatable": 1,
			"highdice": 0,
            "color": "#00FFFF; Cyan",
            "cubed": 3,
            "blocks": [
                0, 0, 0,
                0, 0, 0,
                0, 0, 0,
                
                0, 1, 0,
                1, 0, 1,
                0, 1, 0,
                
                0, 0, 0,
                0, 0, 0,
                0, 0, 0
            ]
        },
        {
            "name": ":) - (:",
			"lifts": 0,
            "rotatable": 1,
			"highdice": 0,
            "color": "#FF00FF; Magenta",
            "cubed": 3,
            "blocks": [
                0, 0, 0,
                0, 0, 0,
                0, 0, 0,
                
                1, 0, 1,
                0, 0, 0,
                1, 0, 1,
                
                0, 0, 0,
                0, 0, 0,
                0, 0, 0
            ]
        },
        {
            "name": "=)",
			"lifts": 0,
            "rotatable": 1,
			"highdice": 0,
            "color": "#800080; Purple",
            "cubed": 3,
            "blocks": [
                0, 0, 0,
                0, 1, 0,
                0, 1, 0,
                
                0, 0, 0,
                0, 1, 0,
                0, 0, 0,
                
                0, 1, 0,
                0, 1, 0,
                0, 0, 0
            ]
        },
        {
            "name": "8-D",
			"lifts": 0,
            "rotatable": 1,
			"highdice": 0,
            "color": "#006400; DarkGreen",
            "cubed": 3,
            "blocks": [
                0, 0, 0,
                0, 0, 0,
                0, 1, 0,
                
                0, 0, 0,
                0, 1, 0,
                0, 1, 0,
                
                0, 1, 0,
                0, 1, 0,
                0, 0, 0
            ]
        },
        {
            "name": "):-|",
			"lifts": 0,
            "rotatable": 1,
			"highdice": 0,
            "color": "#800000; Maroon",
            "cubed": 3,
            "blocks": [
                0, 0, 0,
                0, 0, 0,
                0, 0, 0,
                
                0, 1, 0,
                1, 1, 1,
                0, 1, 0,
                
                0, 0, 0,
                0, 0, 0,
                0, 0, 0
            ]
        },
        {
            "name": ":-P",
			"lifts": 0,
            "rotatable": 1,
			"highdice": 0,
            "color": "#008080; Teal",
            "cubed": 3,
            "blocks": [
                0, 0, 0,
                0, 1, 1,
                0, 0, 0,
                
                0, 0, 0,
                0, 1, 0,
                0, 1, 0,
                
                0, 0, 0,
                0, 1, 0,
                0, 0, 0
            ]
        },
        {
            "name": ">8-)",
			"lifts": 0,
            "rotatable": 1,
			"highdice": 0,
            "color": "#808000; Olive",
            "cubed": 3,
            "blocks": [
                0, 0, 0,
                0, 1, 0,
                0, 1, 0,
                
                0, 0, 0,
                0, 0, 0,
                0, 1, 0,
                
                0, 0, 0,
                0, 1, 0,
                0, 1, 0
            ]
        },
        {
            "name": "(;-)",
			"lifts": 0,
            "rotatable": 1,
			"highdice": 0,
            "color": "#FFD700; Gold",
            "cubed": 3,
            "blocks": [
                0, 0, 0,
                0, 1, 0,
                0, 0, 0,
                
                0, 0, 0,
                0, 0, 0,
                0, 0, 0,
                
                0, 0, 0,
                1, 1, 1,
                0, 0, 0
            ]
        }
	]
}
